cybrex/__init__.py
cybrex/cli.py
cybrex/cybrex_ai.py
cybrex/document_chunker.py
cybrex/exceptions.py
cybrex/llm_manager.py
cybrex/model.py
cybrex/utils.py
cybrex/chains/__init__.py
cybrex/chains/base.py
cybrex/chains/map_reduce.py
cybrex/data_source/base.py
cybrex/data_source/geck_data_source.py
cybrex/prompts/__init__.py
cybrex/prompts/base.py
cybrex/vector_storage/__init__.py
cybrex/vector_storage/base.py
cybrex/vector_storage/qdrant.py
cybrex-1.12.10.dist-info/METADATA
cybrex-1.12.10.dist-info/WHEEL
cybrex-1.12.10.dist-info/entry_points.txt
cybrex-1.12.10.dist-info/top_level.txt
cybrex-1.12.10.dist-info/RECORD
