Metadata-Version: 2.1
Name: cybrex
Version: 1.12.10
Summary: Researching AI
Author: Interdimensional Walker
Project-URL: Homepage, https://github.com/nexus-stc/stc
Classifier: Programming Language :: Python :: 3.8
Requires-Python: >=3.8
Requires-Dist: aiokit >=1.2.3
Requires-Dist: beautifulsoup4 >=4.12.2
Requires-Dist: ctransformers >=0.2.17
Requires-Dist: FlagEmbedding >=1.1.2
Requires-Dist: InstructorEmbedding >=1.0.1
Requires-Dist: izihawa-configurator >=1.0.4
Requires-Dist: izihawa-utils >=1.1.3
Requires-Dist: keybert >=0.7.0
Requires-Dist: langchain >=0.0.222
Requires-Dist: lazy >=1.5
Requires-Dist: lxml >=4.9.3
Requires-Dist: openai >=0.27.8
Requires-Dist: orjson
Requires-Dist: pypdf >=3.12.0
Requires-Dist: pyyaml >=6.0
Requires-Dist: qdrant-client >=1.5.4
Requires-Dist: tiktoken >=0.5.1
Requires-Dist: safetensors ==0.3.1
Requires-Dist: stc-geck >=1.8.35
Requires-Dist: unstructured[html] >=0.10.28
Provides-Extra: petals
Requires-Dist: petals >=2.0.0 ; extra == 'petals'
